feedunify/__init__.py
feedunify/core.py
feedunify/models.py
feedunify/connectors/base.py
feedunify/connectors/rss.py
feedunify/connectors/youtube.py
feedunify-0.3.3.dist-info/licenses/LICENSE
feedunify-0.3.3.dist-info/METADATA
feedunify-0.3.3.dist-info/WHEEL
feedunify-0.3.3.dist-info/top_level.txt
feedunify-0.3.3.dist-info/RECORD
