Metadata-Version: 2.4
Name: feedunify
Version: 0.3.3
Summary: A high-performance, unifying library for data ingestion pipelines from multiple sources.
Author-email: Rudra Kawade <rudrakawade2004@gmail.com>
License: MIT
Project-URL: Homepage, https://github.com/Rudra-K/feedunify
Classifier: Programming Language :: Python :: 3
Classifier: License :: OSI Approved :: MIT License
Classifier: Operating System :: OS Independent
Classifier: Intended Audience :: Developers
Classifier: Topic :: Software Development :: Libraries :: Python Modules
Requires-Python: >=3.8
License-File: LICENSE
Requires-Dist: httpx[http2]>=0.27.0
Requires-Dist: pydantic>=2.7.0
Requires-Dist: feedparser>=6.0.0
Provides-Extra: dev
Requires-Dist: pytest>=8.0.0; extra == "dev"
Requires-Dist: pytest-asyncio>=0.23.0; extra == "dev"
Requires-Dist: black>=24.0.0; extra == "dev"
Dynamic: license-file
